tatc/__init__.py
tatc/config.py
tatc/constants.py
tatc/utils.py
tatc/analysis/__init__.py
tatc/analysis/coverage.py
tatc/analysis/dop.py
tatc/analysis/latency.py
tatc/analysis/ro_coverage.py
tatc/analysis/track.py
tatc/generation/__init__.py
tatc/generation/cells.py
tatc/generation/points.py
tatc/resources/de421.bsp
tatc/schemas/__init__.py
tatc/schemas/architecture.py
tatc/schemas/instrument.py
tatc/schemas/orbit.py
tatc/schemas/point.py
tatc/schemas/satellite.py
tatc-3.4.10.dist-info/licenses/LICENSE
tatc-3.4.10.dist-info/METADATA
tatc-3.4.10.dist-info/WHEEL
tatc-3.4.10.dist-info/top_level.txt
tatc-3.4.10.dist-info/RECORD
