Metadata-Version: 2.4
Name: tatc
Version: 3.4.10
Summary: Tradespace Analysis Toolkit for Constellations (TAT-C)
Author-email: "Paul T. Grogan" <paul.grogan@asu.edu>
License: BSD License
Project-URL: Homepage, https://tatc.readthedocs.io
Project-URL: Repository, https://github.com/code-lab-org/tatc
Project-URL: Documentation, https://tatc.readthedocs.io
Project-URL: Issues, https://github.com/code-lab-org/tatc/issues
Classifier: Programming Language :: Python :: 3
Classifier: Operating System :: OS Independent
Classifier: Development Status :: 4 - Beta
Requires-Python: <3.14,>=3.8
License-File: LICENSE
Requires-Dist: geopandas>=0.13.2
Requires-Dist: joblib
Requires-Dist: numba
Requires-Dist: numpy
Requires-Dist: pandas
Requires-Dist: pydantic>=2.6
Requires-Dist: pyproj
Requires-Dist: shapely>=2
Requires-Dist: skyfield>=1.48
Requires-Dist: sgp4
Requires-Dist: spiceypy
Requires-Dist: typing-extensions
Requires-Dist: pyyaml
Provides-Extra: dev
Requires-Dist: black[jupyter]>=24.2; extra == "dev"
Requires-Dist: coverage; extra == "dev"
Requires-Dist: pylint; extra == "dev"
Requires-Dist: pylint-pydantic; extra == "dev"
Requires-Dist: pytest; extra == "dev"
Provides-Extra: docs
Requires-Dist: autodoc_pydantic>=2; extra == "docs"
Requires-Dist: docutils; extra == "docs"
Requires-Dist: myst-nb; extra == "docs"
Requires-Dist: sphinx>=7; extra == "docs"
Requires-Dist: sphinx-rtd-theme; extra == "docs"
Provides-Extra: examples
Requires-Dist: ipykernel; extra == "examples"
Requires-Dist: matplotlib; extra == "examples"
Requires-Dist: cartopy; extra == "examples"
Provides-Extra: osse
Requires-Dist: netcdf4; extra == "osse"
Requires-Dist: pydap; extra == "osse"
Requires-Dist: rioxarray; extra == "osse"
Requires-Dist: scipy; extra == "osse"
Requires-Dist: scikit-learn; extra == "osse"
Requires-Dist: seaborn; extra == "osse"
Dynamic: license-file
